demalos/__init__.py
demalos/demalos.py
demalos-0.0.4.dist-info/LICENSE
demalos-0.0.4.dist-info/METADATA
demalos-0.0.4.dist-info/WHEEL
demalos-0.0.4.dist-info/top_level.txt
demalos-0.0.4.dist-info/RECORD
