Metadata-Version: 2.1
Name: demalos
Version: 0.0.4
Summary: ALOS 30 m downloader/subsetter
Home-page: UNKNOWN
Author: Amir Souri
Author-email: ahsouri@gmail.com
License: MIT
Platform: UNKNOWN
License-File: LICENSE
Requires-Dist: wget
Requires-Dist: matplotlib
Requires-Dist: rasterio
Requires-Dist: netCDF4
Requires-Dist: shapely
